{
    "6Ww136": {
        "original_url": "https://google.com",
        "custom_domain": "facebook.com",
        "created_at": "2025-04-10 23:30:00",
        "clicks": 1
    },
    "GtW9rQ": {
        "original_url": "https://google.com",
        "custom_domain": "facebook.com",
        "created_at": "2025-04-10 23:30:12",
        "clicks": 0
    },
    "GeYJeM": {
        "original_url": "https://google.com",
        "custom_domain": "default",
        "created_at": "2025-04-10 23:30:32",
        "clicks": 1
    }
}